asyncdictionary/__init__.py
asyncdictionary/client.py
asyncdictionary/definition.py
asyncdictionary/errors.py
asyncdictionary/http.py
asyncdictionary/meaning.py
asyncdictionary/phonetic.py
asyncdictionary/word.py
asyncdictionary-1.2.4.dist-info/LICENSE.txt
asyncdictionary-1.2.4.dist-info/METADATA
asyncdictionary-1.2.4.dist-info/WHEEL
asyncdictionary-1.2.4.dist-info/top_level.txt
asyncdictionary-1.2.4.dist-info/RECORD
