Metadata-Version: 2.1
Name: asyncdictionary
Version: 1.2.4
Summary: An asynchronous wrapper in python for the https://dictionaryapi.dev API
Home-page: https://github.com/Ay-355/asyncdictionary
Author: Ay355
License: MIT
Project-URL: Documentation, https://github.com/Ay-355/asyncdictionary/blob/master/Documentation.md
Project-URL: Issue Tracker, https://github.com/Ay-355/asyncdictionary/issues
Keywords: dictionary,api,wrapper,asyncdictionary,async,pythondictionary,dictionary api,asyncdictionary api
Platform: UNKNOWN
Classifier: License :: OSI Approved :: MIT License
Classifier: Intended Audience :: Developers
Classifier: Natural Language :: English
Classifier: Programming Language :: Python :: 3.6
Classifier: Programming Language :: Python :: 3.7
Classifier: Programming Language :: Python :: 3.8
Classifier: Programming Language :: Python :: 3.9
Requires-Python: >=3.6.0
License-File: LICENSE.txt
Requires-Dist: aiohttp
